README.md
salami-predict
setup.py
salami/__init__.py
salami.egg-info/PKG-INFO
salami.egg-info/SOURCES.txt
salami.egg-info/dependency_links.txt
salami.egg-info/requires.txt
salami.egg-info/top_level.txt
salami/E13000_P11/kfactor_objects.pkl
salami/E13000_P11/kfactor_weights.hdf5
salami/E13000_P12/kfactor_objects.pkl
salami/E13000_P12/kfactor_weights.hdf5
salami/E13000_P13/kfactor_objects.pkl
salami/E13000_P13/kfactor_weights.hdf5
salami/E13000_P14/kfactor_objects.pkl
salami/E13000_P14/kfactor_weights.hdf5
salami/E13000_P15/kfactor_objects.pkl
salami/E13000_P15/kfactor_weights.hdf5
salami/E13000_P16/kfactor_objects.pkl
salami/E13000_P16/kfactor_weights.hdf5
salami/E13000_P17/kfactor_objects.pkl
salami/E13000_P17/kfactor_weights.hdf5
salami/E13000_P18/kfactor_objects.pkl
salami/E13000_P18/kfactor_weights.hdf5
salami/E13000_P22/kfactor_objects.pkl
salami/E13000_P22/kfactor_weights.hdf5
salami/E13000_P23/kfactor_objects.pkl
salami/E13000_P23/kfactor_weights.hdf5
salami/E13000_P24/kfactor_objects.pkl
salami/E13000_P24/kfactor_weights.hdf5
salami/E13000_P25/kfactor_objects.pkl
salami/E13000_P25/kfactor_weights.hdf5
salami/E13000_P26/kfactor_objects.pkl
salami/E13000_P26/kfactor_weights.hdf5
salami/E13000_P27/kfactor_objects.pkl
salami/E13000_P27/kfactor_weights.hdf5
salami/E13000_P28/kfactor_objects.pkl
salami/E13000_P28/kfactor_weights.hdf5
salami/E13000_P33/kfactor_objects.pkl
salami/E13000_P33/kfactor_weights.hdf5
salami/E13000_P34/kfactor_objects.pkl
salami/E13000_P34/kfactor_weights.hdf5
salami/E13000_P35/kfactor_objects.pkl
salami/E13000_P35/kfactor_weights.hdf5
salami/E13000_P36/kfactor_objects.pkl
salami/E13000_P36/kfactor_weights.hdf5
salami/E13000_P37/kfactor_objects.pkl
salami/E13000_P37/kfactor_weights.hdf5
salami/E13000_P38/kfactor_objects.pkl
salami/E13000_P38/kfactor_weights.hdf5
salami/E13000_P44/kfactor_objects.pkl
salami/E13000_P44/kfactor_weights.hdf5
salami/E13000_P45/kfactor_objects.pkl
salami/E13000_P45/kfactor_weights.hdf5
salami/E13000_P46/kfactor_objects.pkl
salami/E13000_P46/kfactor_weights.hdf5
salami/E13000_P47/kfactor_objects.pkl
salami/E13000_P47/kfactor_weights.hdf5
