Metadata-Version: 1.0
Name: salami
Version: 0.3.2
Summary: Lightweight NLO BSM cross-sections, to go
Home-page: UNKNOWN
Author: Andy Buckley, Abhijeet Gangan, Jack Murphy
Author-email: andy.buckley@cern.ch
License: GPL
Keywords: supersymmetry susy slha hep physics particle cross-section xsec prospino
Platform: UNKNOWN
